Metadata-Version: 2.1
Name: pyloglib
Version: 1.0.7
Summary: Python logging library
Home-page: UNKNOWN
Author: DanishDeveloper
License: MIT
Keywords: pyloglib
Platform: UNKNOWN
Classifier: Development Status :: 5 - Production/Stable
Classifier: Intended Audience :: Education
Classifier: Operating System :: Microsoft :: Windows :: Windows 10
Classifier: License :: OSI Approved :: MIT License
Classifier: Programming Language :: Python :: 3
License-File: LICENCE.txt
